AUTHOR.txt
CHANGES.txt
LICENSE.txt
README.txt
bootstrap.py
buildout.cfg
ez_setup.py
setup.cfg
setup.py
repoze/__init__.py
repoze.squeeze.egg-info/PKG-INFO
repoze.squeeze.egg-info/SOURCES.txt
repoze.squeeze.egg-info/dependency_links.txt
repoze.squeeze.egg-info/entry_points.txt
repoze.squeeze.egg-info/namespace_packages.txt
repoze.squeeze.egg-info/not-zip-safe
repoze.squeeze.egg-info/requires.txt
repoze.squeeze.egg-info/top_level.txt
repoze/squeeze/README.txt
repoze/squeeze/__init__.py
repoze/squeeze/processor.py
repoze/squeeze/tests.py