Metadata-Version: 1.0
Name: repoze.squeeze
Version: 0.4.4
Summary: WSGI middleware for statistical HTML browser resource squeezing.
Home-page: http://www.repoze.org
Author: Malthe Borch and Stefan Eletzhofer
Author-email: repoze-dev@lists.repoze.org
License: BSD-derived (http://www.repoze.org/LICENSE.txt)
Keywords: web middleware wsgi css js squeeze merging statistics cache
Platform: UNKNOWN
Classifier: Development Status :: 4 - Beta
Classifier: Intended Audience :: Developers
Classifier: Programming Language :: Python
Classifier: Topic :: Internet :: WWW/HTTP
Classifier: Topic :: Internet :: WWW/HTTP :: WSGI
Classifier: Topic :: Internet :: WWW/HTTP :: WSGI :: Application
